Metadata-Version: 2.4
Name: meshly
Version: 1.3.8
Summary: High-level abstractions and utilities for working with meshoptimizer
Author: Open Orion
Maintainer: Open Orion
License: MIT
Project-URL: Homepage, https://github.com/OpenOrion/meshly
Project-URL: Repository, https://github.com/OpenOrion/meshly
Project-URL: Bug Tracker, https://github.com/OpenOrion/meshly/issues
Project-URL: Documentation, https://github.com/OpenOrion/meshly#readme
Keywords: mesh,3d,graphics,meshoptimizer,optimization
Classifier: Programming Language :: Python :: 3
Classifier: Programming Language :: Python :: 3.8
Classifier: Programming Language :: Python :: 3.9
Classifier: Programming Language :: Python :: 3.10
Classifier: Programming Language :: Python :: 3.11
Classifier: Programming Language :: Python :: 3.12
Classifier: License :: OSI Approved :: MIT License
Classifier: Operating System :: OS Independent
Classifier: Topic :: Scientific/Engineering :: Mathematics
Classifier: Topic :: Multimedia :: Graphics :: 3D Modeling
Classifier: Intended Audience :: Developers
Classifier: Intended Audience :: Science/Research
Classifier: Development Status :: 4 - Beta
Requires-Python: >=3.8
Requires-Dist: numpy>=1.19.0
Requires-Dist: meshoptimizer==0.2.20a5
Requires-Dist: pydantic>=2.0.0
Provides-Extra: jax
Requires-Dist: jax; extra == "jax"
Requires-Dist: jaxlib; extra == "jax"
